{"csc":{"name":"csc","alias":"客户服务接口","algorithm":"cjhash","accept":"","channelType":"unicast","match":"none","shared":{},"validDestinations":{"csc1":{"name":"csc1","protocol":"rio-tcp","inetHost":"192.168.201.210","useShared":false,"port":"16000","props":{"workThreadCount":"4"}},"csc2":{"name":"csc2","protocol":"rio-tcp","inetHost":"192.168.201.210","useShared":false,"port":"16002","props":{"workThreadCount":"4"}}},"invalidDestinations":{}},"sns":{"name":"sns","alias":"连接到互动中心云","algorithm":"cjhash","accept":"","channelType":"unicast","match":"none","shared":{},"validDestinations":{"c-dc1":{"name":"c-dc1","protocol":"rio-tcp","inetHost":"192.168.201.210","useShared":false,"port":"13000","props":{"bossThreadCount":"1","workThreadCount":"4"}}},"invalidDestinations":{}},"sosdb":{"name":"sosdb","alias":"服务操作系统后台","algorithm":"cjhash","accept":"","channelType":"unicast","match":"none","shared":{},"validDestinations":{"sosdb-210-2":{"name":"sosdb-210-2","protocol":"rio-tcp","inetHost":"192.168.201.210","useShared":false,"port":"13100","props":{"bossThreadCount":"1","workThreadCount":"4"},"cause":""}},"invalidDestinations":{"sosdb2":{"name":"sosdb2","protocol":"rio-tcp","inetHost":"localhost","useShared":false,"port":"10000","props":{"bossThreadCount":"1","workThreadCount":"0"},"cause":""},"sosdb-210-1":{"name":"sosdb-210-1","protocol":"rio-tcp","inetHost":"192.168.201.210","useShared":false,"port":"13102","props":{"bossThreadCount":"1","workThreadCount":"0"},"cause":""},"sosdb1":{"name":"sosdb1","protocol":"rio-tcp","inetHost":"localhost","useShared":false,"port":"10000","props":{"bossThreadCount":"1","workThreadCount":"0"},"cause":""}}}}